Metadata-Version: 1.1
Name: pyshlang
Version: 0.1.1
Summary: Pysh language implementation
Home-page: https://github.com/sfuller/pysh
Author: Sam Fuller
Author-email: sam@samfullerstudios.com
License: Apache
Platform: UNKNOWN
Classifier: Development Status :: 2 - Pre-Alpha
Classifier: Intended Audience :: Developers
Classifier: License :: OSI Approved :: Apache Software License
Classifier: Programming Language :: Python :: 3
Classifier: Programming Language :: Python :: 3 :: Only
Classifier: Programming Language :: Python :: 3.6
